devices/__init__.py
devices/deformable_mirror_Mirao52e.py
devices/device_template.py
devices/etl_controller_Optotune.py
devices/hamamatsu_camera.py
devices/lightsheet_generator.py
devices/motion_controller_Thorlabs_MCM3000.py
devices/stage_ASI_MS2000.py
kekse/__init__.py
kekse/kekse.py
tests/__init__.py
tests/test_protokeks.py
kekse-0.1.dist-info/LICENSE
kekse-0.1.dist-info/METADATA
kekse-0.1.dist-info/WHEEL
kekse-0.1.dist-info/top_level.txt
kekse-0.1.dist-info/RECORD
